advanced_caching/__init__.py
advanced_caching/_decorator_common.py
advanced_caching/_schedulers.py
advanced_caching/decorators.py
advanced_caching/storage.py
advanced_caching-0.2.0.dist-info/METADATA
advanced_caching-0.2.0.dist-info/WHEEL
advanced_caching-0.2.0.dist-info/licenses/LICENSE
advanced_caching-0.2.0.dist-info/RECORD
