Metadata-Version: 2.4
Name: advanced-caching
Version: 0.2.0
Summary: Production-ready composable caching with TTL, SWR, and background refresh patterns for Python.
Project-URL: Homepage, https://github.com/agkloop/advanced_caching
Project-URL: Repository, https://github.com/agkloop/advanced_caching
Project-URL: Documentation, https://github.com/agkloop/advanced_caching#readme
Project-URL: Issues, https://github.com/agkloop/advanced_caching/issues
Maintainer-email: ahmed <ahmed99kamal@gmail.com>
License: MIT
License-File: LICENSE
Keywords: apscheduler,cache,python,redis,scheduler,stale-while-revalidate,swr,ttl
Classifier: Development Status :: 4 - Beta
Classifier: Intended Audience :: Developers
Classifier: License :: OSI Approved :: MIT License
Classifier: Operating System :: OS Independent
Classifier: Programming Language :: Python
Classifier: Programming Language :: Python :: 3
Classifier: Programming Language :: Python :: 3.10
Classifier: Programming Language :: Python :: 3.11
Classifier: Programming Language :: Python :: 3.12
Classifier: Topic :: Software Development :: Libraries
Classifier: Topic :: System :: Distributed Computing
Classifier: Typing :: Typed
Requires-Python: >=3.10
Requires-Dist: apscheduler>=3.10
Requires-Dist: orjson>=3.11.5
Provides-Extra: dev
Requires-Dist: pytest-cov>=4.0; extra == 'dev'
Requires-Dist: pytest>=8.2; extra == 'dev'
Provides-Extra: redis
Requires-Dist: redis>=5.0; extra == 'redis'
